CountTo/Decorators.py
CountTo/Wrapper.py
CountTo/__init__.py
CountToCython-0.0.4.dist-info/METADATA
CountToCython-0.0.4.dist-info/WHEEL
CountToCython-0.0.4.dist-info/top_level.txt
CountToCython-0.0.4.dist-info/RECORD
